mimosa/__init__.py
mimosa/company.py
mimosa/db.py
mimosa/examples.py
mimosa/main.py
mimosa/migrate.py
mimosa/models.py
mimosa/presets.py
mimosa/project.py
mimosa/rtdb.py
mimosa/sitekey.py
mimosa/theme.py
mimosa/user.py
mimosa/utils.py
mimosa/validation_test.ipynb
mimosa/validators.py
mimosa/version.py
mimosa_monomer-0.2.0.dist-info/entry_points.txt
mimosa_monomer-0.2.0.dist-info/LICENSE.md
mimosa_monomer-0.2.0.dist-info/WHEEL
mimosa_monomer-0.2.0.dist-info/METADATA
mimosa_monomer-0.2.0.dist-info/RECORD
