Metadata-Version: 2.1
Name: mimosa-monomer
Version: 0.2.0
Summary: CLI for Stilt 2 database.
Author: Daniel Hampton
Author-email: dhampton084@gmail.com
Requires-Python: >=3.6,<4.0
Classifier: Environment :: Console
Classifier: Operating System :: OS Independent
Classifier: Programming Language :: Python :: 3
Classifier: Programming Language :: Python :: 3.6
Classifier: Programming Language :: Python :: 3.7
Classifier: Programming Language :: Python :: 3.8
Classifier: Programming Language :: Python :: 3.9
Classifier: Topic :: Database
Classifier: Topic :: Utilities
Requires-Dist: attrs (>=19.3.0,<20.0.0)
Requires-Dist: cerberus (>=1.3.2,<2.0.0)
Requires-Dist: click (>=7.0,<8.0)
Requires-Dist: cutie (>=0.2.2,<0.3.0)
Requires-Dist: firebase-admin (>=3.2.1,<4.0.0)
Requires-Dist: halo (>=0.0.28,<0.0.29)
Requires-Dist: typer (>=0.3.2,<0.4.0)
